<?xml version="1.0" standalone="yes"?>
<!-- Example data from instrument, trimmed down to an illustrative subset. -->
<NewDataSet>
  <UserTest>
    <TestMethod_nm>ExampleTestMethod</TestMethod_nm>
    <User_nm>Administrator</User_nm>
    <Product_nm>ExampleProject</Product_nm>
    <Material_nm>ExampleMaterial2</Material_nm>
    <Material_Batch_nm>Lot3</Material_Batch_nm>
    <DataPool_id>197</DataPool_id>
    <Material_id>105</Material_id>
    <Created_dt>2024-01-01T00:00:00.000-00:00</Created_dt>
  </UserTest>
  <Material>
    <Material_id>105</Material_id>
    <Material_nm>ExampleMaterial2</Material_nm>
    <Material_Group_id>101</Material_Group_id>
  </Material>
  <Material_Group>
    <Material_Group_id>101</Material_Group_id>
    <Material_Group_nm>ExampleGroup</Material_Group_nm>
  </Material_Group>
  <DataInterval>
    <DataPool_id>197</DataPool_id>
    <DataInterval_id>1114</DataInterval_id>
  </DataInterval>
  <DataInterval>
    <DataPool_id>197</DataPool_id>
    <DataInterval_id>1115</DataInterval_id>
  </DataInterval>
  <DataInterval>
    <DataPool_id>197</DataPool_id>
    <DataInterval_id>1116</DataInterval_id>
  </DataInterval>
  <DataSample>
    <DataInterval_id>1114</DataInterval_id>
    <Sample_Start_dt>2024-01-01T00:10:00.000-00:00</Sample_Start_dt>
    <AmbientTemp_nb>19.37638</AmbientTemp_nb>
    <Result_nb>1091.78455</Result_nb>
    <K_Result_nb>0.7444357</K_Result_nb>
    <Valid_yn>Y</Valid_yn>
  </DataSample>
  <DataSample>
    <DataInterval_id>1115</DataInterval_id>
    <Sample_Start_dt>2024-01-01T00:11:00.000-00:00</Sample_Start_dt>
    <AmbientTemp_nb>19.4154587</AmbientTemp_nb>
    <Result_nb>1087.40051</Result_nb>
    <K_Result_nb>0.739810169</K_Result_nb>
    <Valid_yn>Y</Valid_yn>
  </DataSample>
  <DataSample>
    <DataInterval_id>1116</DataInterval_id>
    <Sample_Start_dt>2024-01-01T00:12:00.000-00:00</Sample_Start_dt>
    <AmbientTemp_nb>19.44345</AmbientTemp_nb>
    <Result_nb>1096.30713</Result_nb>
    <K_Result_nb>0.7492129</K_Result_nb>
    <Valid_yn>Y</Valid_yn>
  </DataSample>
</NewDataSet>
